Metadata-Version: 2.1
Name: boxly
Version: 0.1.1
Summary: small, underimplemented geometry package for bounding boxes
Home-page: https://github.com/prhbrt/boxly
Author: H.T. Kruitbosch
Author-email: Herbert Kruitbosch <boxly@prinsherbert.nl>
Project-URL: Homepage, https://github.com/prhbrt/boxly
Project-URL: Issues, https://github.com/prhbrt/boxly/issues
Classifier: Programming Language :: Python :: 3
Classifier: License :: OSI Approved :: MIT License
Classifier: Operating System :: OS Independent
Requires-Python: >=3.0
License-File: LICENSE.txt
